most_sdk/__init__.py
most_sdk/client.py
most_sdk/exceptions.py
most_sdk/routes.py
most_sdk-0.1.1.dist-info/METADATA
most_sdk-0.1.1.dist-info/WHEEL
most_sdk-0.1.1.dist-info/RECORD
