Metadata-Version: 2.1
Name: most_sdk
Version: 0.1.1
Summary: 
Author: Tecnologia BYX
Author-email: tecnologia@grupobyx.com.br
Requires-Python: >=3.9,<4.0
Classifier: Programming Language :: Python :: 3
Classifier: Programming Language :: Python :: 3.9
Classifier: Programming Language :: Python :: 3.10
Classifier: Programming Language :: Python :: 3.11
Classifier: Programming Language :: Python :: 3.12
Requires-Dist: pre-commit (>=3.6.2,<4.0.0)
Requires-Dist: requests (>=2.31.0,<3.0.0)
Requires-Dist: six (>=1.16.0,<2.0.0)
